texbuild/__init__.py
texbuild/build.py
texbuild-0.3.dist-info/LICENSE
texbuild-0.3.dist-info/METADATA
texbuild-0.3.dist-info/WHEEL
texbuild-0.3.dist-info/entry_points.txt
texbuild-0.3.dist-info/top_level.txt
texbuild-0.3.dist-info/RECORD
