Metadata-Version: 2.1
Name: texbuild
Version: 0.3
Summary: Build system for LaTeX documents.
Author-email: Daniel Sank <sank.daniel@gmail.com>
License: MIT License
Project-URL: Homepage, https://github.com/DanielSank/texbuild
Project-URL: Bug Tracker, https://github.com/DanielSank/texbuild/issues
Keywords: latex
Classifier: Programming Language :: Python :: 3
Classifier: License :: OSI Approved :: MIT License
Classifier: Operating System :: OS Independent
Requires-Python: >=3.7
License-File: LICENSE
Requires-Dist: numpy
Requires-Dist: attrs
